README.md
setup.py
holey/__init__.py
holey/draw.py
holey/loop.py
holey/point.py
holey/rasterize.py
holey.egg-info/PKG-INFO
holey.egg-info/SOURCES.txt
holey.egg-info/dependency_links.txt
holey.egg-info/requires.txt
holey.egg-info/top_level.txt